driver_makery/__init__.py
driver_makery/build.py
driver_makery/cleaner.py
driver_makery/cli.py
driver_makery/codegen.py
driver_makery/config.py
driver_makery/gemini_client.py
driver_makery/pdf_extract.py
driver_makery/splitter.py
driver_makery/utils.py
driver_makery-0.2.0.dist-info/licenses/LICENSE.txt
driver_makery-0.2.0.dist-info/METADATA
driver_makery-0.2.0.dist-info/WHEEL
driver_makery-0.2.0.dist-info/entry_points.txt
driver_makery-0.2.0.dist-info/top_level.txt
driver_makery-0.2.0.dist-info/RECORD
