Metadata-Version: 2.4
Name: driver-makery
Version: 0.2.0
Summary: PDF→텍스트→분할→Gemini→C 헤더 생성 파이프라인
Author-email: Your Name <you@example.com>
License: MIT
Requires-Python: >=3.9
License-File: LICENSE.txt
Dynamic: license-file
